cedarscript_grammar/__init__.py
cedarscript_grammar/libtree-sitter-cedarscript.amd64.so
cedarscript_grammar/libtree-sitter-cedarscript.arm64.so
cedarscript_grammar/libtree-sitter-cedarscript.dll
version/__init__.py
version/_version.py
cedarscript_grammar-0.7.0.dist-info/LICENSE
cedarscript_grammar-0.7.0.dist-info/METADATA
cedarscript_grammar-0.7.0.dist-info/WHEEL
cedarscript_grammar-0.7.0.dist-info/top_level.txt
cedarscript_grammar-0.7.0.dist-info/RECORD
