Metadata-Version: 2.1
Name: cedarscript-grammar
Version: 0.7.0
Summary: CEDARScript grammar.js for tree-sitter
Author-email: Elifarley <cedarscript@orgecc.com>
License: Apache-2.0
Project-URL: Homepage, https://github.com/CEDARScript/cedarscript-grammar#readme
Project-URL: Repository, https://github.com/CEDARScript/cedarscript-grammar.git
Project-URL: Documentation, https://github.com/CEDARScript/cedarscript-grammar#readme
Project-URL: Bug Tracker, https://github.com/CEDARScript/cedarscript-grammar/issues
Keywords: parser,tree-sitter,ast,cedarscript,code-editing,refactoring,code-analysis,sql-like,ai-assisted-development,python-binding
Classifier: Development Status :: 3 - Alpha
Classifier: Intended Audience :: Developers
Classifier: License :: OSI Approved :: Apache Software License
Classifier: Programming Language :: Python :: 3
Classifier: Topic :: Software Development :: Compilers
Classifier: Topic :: Text Processing :: Linguistic
Classifier: Typing :: Typed
Requires-Python: >=3.8
License-File: LICENSE
Requires-Dist: tree-sitter<0.22
